{
    "domain": "http://joelsimon.net/",
    "storage": "https://storage.googleapis.com/joel-simon-net.appspot.com/",
    "labels": {
        "generative": "rgb(176, 172, 249)",
        "sculpture": "rgb(192, 114, 234)",
        "code": "rgb(255, 193, 213)",
        "lighting": "rgb(252, 116, 182)",
        "web": "rgb(110, 244, 217)",
        "video": "rgb(252, 116, 182)"
    },
    
    "projects": [
        {
            "name": "Virtual Corals",
            "labels": ["generative", "code", "video"],
            "img": "imgs/virtual-corals/icon.png",
            "hide": true,
            "year": 2017
        },
        {
            "name": "Ecosystem Modelling",
            "labels": ["generative", "code", "video"],
            "img": "imgs/ecosystem-modelling/005300.jpg",
            "hide": false,
            "description": "Visualizing ecosystem simulations",
            "year": 2017
        },
        {
            "name": "Figuration",
            "labels": [ "video"],
            "img": "imgs/figuration.jpg",
            "description": "A si-fi short film.",
            "year": 2017

        },
        {
            "name": "Plant Lamp",
            "labels": ["lighting"],
            "img": "imgs/plant-lamp/IMG_5435_4.jpg",
            "year": 2017
        },
        {
            "name": "Desk Lamp 2",
            "labels": ["lighting"],
            "img": "imgs/desk-lamp-2/icon.jpg",
            "year": 2017
        },
        {
            "name": "Simon Lamps",
            "labels": ["lighting", "web", "code"],
            "img": "imgs/simon-lamps/icon.jpg",
            "year": 2016
        },
        {
            "name": "Desk Lamp 1",
            "labels": ["lighting"],
            "img": "imgs/desk_lamp_1b/icon2.jpg",
            "year": 2016
        },
        {
            "name": "Wall Lamp",
            "labels": ["lighting"],
            "img": "imgs/wall-lamp/wall-lamp-icon.jpg",
            "year": 2016
        },
        {
            "name": "Sculpture Drop",
            "labels": ["generative", "sculpture"],
            "img": "imgs/sculpture-drop.jpg",
            "year": 2016
        },
        {
            "name": "Table lamp 3",
            "labels": ["lighting"],
            "img": "imgs/table-lamp-3/icon.jpg",
            "year": 2015
        },

        {
            "name": "Tanya",
            "labels": ["sculpture"],
            "img": "imgs/tanya.jpg",
            "year": 2015
        },
        {
            "name": "Table lamp 2",
            "labels": ["lighting"],
            "img": "imgs/table-lamp-2/icon.jpg",
            "year": 2015
        },
        {
            "name": "Facebook Graffiti",
            "labels": ["code", "web"],
            "img": "imgs/fb-graffiti.png",
            "year": 2015
        },

        {
            "name": "Scrap",
            "labels": ["web", "code"],
            "img": "imgs/scrap.png",
            "year": 2015
        },
        {
            "name": "Slice",
            "labels": ["generative", "sculpture", "code"],
            "img": "imgs/slice.jpg",
            "year": 2014
        },
        {
            "name": "Graph Contraction",
            "labels": ["generative", "code", "sculpture"],
            "img": "imgs/graph-contraction/graph-contraction.png",
            "year": 2014
        },
        {
            "name": "Maria",
            "labels": ["sculpture"],
            "img": "imgs/maria/icon2.png",
            "year": 2013
        },
        {
            "name": "Image To Paint",
            "labels": ["generative", "code"],
            "img": "imgs/image-to-paint/icon.jpg",
            "year": 2012
        },
        {
            "name": "Head in Hands",
            "labels": ["sculpture"],
            "img": "imgs/head-in-hands/icon.JPG",
            "year": 2012
        },
        {
            "name": "Cornered Hands",
            "labels": ["sculpture"],
            "img": "imgs/cornered-hands/icon.jpg",
            "year": 2012
        },
        {
            "name": "Small-talk Robot",
            "labels": ["code"],
            "img": "imgs/smalltalk/smalltalk_square.jpg",
            "year": 2012
        },
        {
            "name": "Mosaic Table",
            "labels": [],
            "img": "imgs/mosaic-table/table_square.jpg",
            "year": 2007
        }
    ]
}
